{"generation": {}, "info": {"participant": 151, "exposed": true, "lab": false, "start": 1488822488897, "counterbalance": 6, "condition": "XOR", "browser": {"platform": "Win32", "userAgent": "Mozilla/5.0 (Windows NT 6.1; Win64; x64) AppleWebKit/537.36 (KHTML, like Gecko) Chrome/56.0.2924.87 Safari/537.36"}}, "experiment": {"Paradigm": "TACL", "Stimuli": "Size-Color Squares", "Experiment": "Generating-Categories"}, "observation": {"11": {"stimulus": 10, "trial": 11, "rt": 4052}, "10": {"stimulus": 80, "trial": 10, "rt": 961}, "1": {"stimulus": 80, "trial": 1, "rt": 1579}, "0": {"stimulus": 0, "trial": 0, "rt": 1727}, "3": {"stimulus": 70, "trial": 3, "rt": 1075}, "2": {"stimulus": 10, "trial": 2, "rt": 1258}, "5": {"stimulus": 80, "trial": 5, "rt": 955}, "4": {"stimulus": 10, "trial": 4, "rt": 915}, "7": {"stimulus": 0, "trial": 7, "rt": 875}, "6": {"stimulus": 70, "trial": 6, "rt": 915}, "9": {"stimulus": 70, "trial": 9, "rt": 907}, "8": {"stimulus": 0, "trial": 8, "rt": 834}}, "generalization": {}}