{"generation": {}, "info": {"participant": 200, "exposed": true, "lab": false, "start": 1488822906262, "counterbalance": 2, "condition": "Cluster", "browser": {"platform": "Win32", "userAgent": "Mozilla/5.0 (Windows NT 6.3; WOW64; Trident/7.0; Touch; .NET4.0E; .NET4.0C; .NET CLR 3.5.30729; .NET CLR 2.0.50727; .NET CLR 3.0.30729; Tablet PC 2.0; MASMJS; rv:11.0) like Gecko"}}, "experiment": {"Paradigm": "TACL", "Stimuli": "Size-Color Squares", "Experiment": "Generating-Categories"}, "observation": {"11": {"stimulus": 14, "trial": 11, "rt": 1446}, "10": {"stimulus": 34, "trial": 10, "rt": 1635}, "1": {"stimulus": 16, "trial": 1, "rt": 1644}, "0": {"stimulus": 14, "trial": 0, "rt": 2294}, "3": {"stimulus": 32, "trial": 3, "rt": 1434}, "2": {"stimulus": 34, "trial": 2, "rt": 1492}, "5": {"stimulus": 16, "trial": 5, "rt": 5514}, "4": {"stimulus": 34, "trial": 4, "rt": 1468}, "7": {"stimulus": 32, "trial": 7, "rt": 2281}, "6": {"stimulus": 14, "trial": 6, "rt": 3423}, "9": {"stimulus": 32, "trial": 9, "rt": 1903}, "8": {"stimulus": 16, "trial": 8, "rt": 2134}}, "generalization": {}}